ezgitup/__init__.py
ezgitup/uploader.py
ezgitup-0.2.4.dist-info/METADATA
ezgitup-0.2.4.dist-info/WHEEL
ezgitup-0.2.4.dist-info/entry_points.txt
ezgitup-0.2.4.dist-info/licenses/LICENSE
ezgitup-0.2.4.dist-info/RECORD
