Metadata-Version: 2.4
Name: ezgitup
Version: 0.2.4
Summary: A simple tool to upload files to GitHub repositories
Project-URL: Homepage, https://github.com/keceli/EzGitUp
Project-URL: Bug Tracker, https://github.com/keceli/EzGitUp/issues
Author-email: Murat Keçeli <keceli@gmail.com>
License-Expression: Apache-2.0
License-File: LICENSE
Classifier: License :: OSI Approved :: Apache Software License
Classifier: Operating System :: OS Independent
Classifier: Programming Language :: Python :: 3
Requires-Python: >=3.6
Requires-Dist: importlib-metadata>=4.6.0; python_version < '3.8'
Requires-Dist: requests>=2.25.1
